QuasarCode/__about__.py
QuasarCode/__init__.py
QuasarCode/_global_settings.py
QuasarCode/Data/_AuthorInfomation.py
QuasarCode/Data/_PersonInfomation.py
QuasarCode/Data/_Rect.py
QuasarCode/Data/_Rect3D.py
QuasarCode/Data/_VersionInformation.py
QuasarCode/Data/__init__.py
QuasarCode/Games/__init__.py
QuasarCode/Games/Cards/_CardGroup.py
QuasarCode/Games/Cards/_CardQueue.py
QuasarCode/Games/Cards/_CardStack.py
QuasarCode/Games/Cards/_Deck.py
QuasarCode/Games/Cards/_IPlayingCard.py
QuasarCode/Games/Cards/_PlayingCard.py
QuasarCode/Games/Cards/__init__.py
QuasarCode/Games/Dice/_Dice12.py
QuasarCode/Games/Dice/_Dice6.py
QuasarCode/Games/Dice/_Dice8.py
QuasarCode/Games/Dice/_DiceCup.py
QuasarCode/Games/Dice/_IDice.py
QuasarCode/Games/Dice/_NDice.py
QuasarCode/Games/Dice/__init__.py
QuasarCode/Games/Spinners/_ISpinner.py
QuasarCode/Games/Spinners/_Spinner.py
QuasarCode/Games/Spinners/__init__.py
QuasarCode/IO/__init__.py
QuasarCode/IO/Caching/_CacheTarget.py
QuasarCode/IO/Caching/_CacheTargetFactory.py
QuasarCode/IO/Caching/_Cacheable.py
QuasarCode/IO/Caching/_CacheableList.py
QuasarCode/IO/Caching/__init__.py
QuasarCode/IO/Checkpointing/_CheckpointBase.py
QuasarCode/IO/Checkpointing/_CheckpointController.py
QuasarCode/IO/Checkpointing/_CheckpointState.py
QuasarCode/IO/Checkpointing/_PickleCheckpoint.py
QuasarCode/IO/Checkpointing/__init__.py
QuasarCode/IO/Configurations/_ConfigsBase.py
QuasarCode/IO/Configurations/__init__.py
QuasarCode/IO/Configurations/_json.py
QuasarCode/IO/Configurations/_properties.py
QuasarCode/IO/Configurations/_yaml.py
QuasarCode/IO/Text/__init__.py
QuasarCode/IO/Text/_console.py
QuasarCode/IO/Text/_stopwatch.py
QuasarCode/MPI/_MPI_Config_Base.py
QuasarCode/MPI/__init__.py
QuasarCode/MPI/_dependant_dummy/__init__.py
QuasarCode/MPI/_dependant_dummy/_convinience_methods.py
QuasarCode/MPI/_dependant_mpi/__init__.py
QuasarCode/MPI/_dependant_mpi/_convinience_methods.py
QuasarCode/MPI/_independant_dummy/_mpi_config.py
quasarcode-0.31.1.dist-info/METADATA
quasarcode-0.31.1.dist-info/WHEEL
quasarcode-0.31.1.dist-info/licenses/LICENSE.txt
quasarcode-0.31.1.dist-info/RECORD
