Metadata-Version: 2.4
Name: QuasarCode
Version: 0.31.1
Summary: A general purpose library for Python applications.
Project-URL: Documentation, https://github.com/QuasarX1/QuasarCode/blob/master/README.md
Project-URL: Issues, https://github.com/QuasarX1/QuasarCode/issues
Project-URL: Source, https://github.com/QuasarX1/QuasarCode
Author-email: "Christopher J. R. Rowe" <contact@cjrrowe.com>
License: Copyright (c) 2024-present Christopher J. R. Rowe <contact@cjrrowe.com>
License-File: LICENSE.txt
Classifier: Development Status :: 4 - Beta
Classifier: Natural Language :: English
Classifier: Operating System :: OS Independent
Classifier: Programming Language :: Python
Classifier: Programming Language :: Python :: 3.10
Classifier: Programming Language :: Python :: 3.11
Classifier: Programming Language :: Python :: 3.12
Classifier: Programming Language :: Python :: 3.13
Classifier: Programming Language :: Python :: Implementation :: CPython
Classifier: Programming Language :: Python :: Implementation :: PyPy
Classifier: Topic :: Software Development
Requires-Python: >=3.7
Requires-Dist: matplotlib
Requires-Dist: numpy
Requires-Dist: pyyaml
Requires-Dist: scipy
Requires-Dist: typing-extensions
Requires-Dist: unyt
